{
    "changelogs": [
        {
            "version": "1.0.0",
            "date": "11/22/2025",
            "changes": [
                "Initial release"
            ]
        },
        {
            "version": "1.0.1",
            "date": "11/23/2025",
            "changes": [
                "Added `/about`, `/wonderland` cover images now upload to Discord CDN and use it to load instead of loading from HoYo servers. Introduce `/changelogs` command to view changelogs."
            ]
        },
        {
            "version": "1.0.2",
            "date": "12/03/2025",
            "changes": [
                "fix: Previous GUID being retained when running `/wonderland`"
            ]
        },
        {
            "version": "1.0.3",
            "date": "01/15/2026",
            "changes": [
                "fix: Prevented /wonderland command from failing when embed descriptions exceed Discord limits",
                "improve: Truncate long level descriptions for better mobile readability",
                "improve: Allow commands to be used in Direct Messages (DMs)",
                "internal: Added daily rotating log files for improved debugging and stability"
            ]
        }
    ]
}